iPAGE2/MI.py
iPAGE2/__init__.py
iPAGE2/body.py
iPAGE2/filter_db.py
iPAGE2/heatmap.py
iPAGE2/ipage2.py
iPAGE2/preprocess.py
iPAGE2/stat_ipage.py
iPAGE_2-0.0.1.data/scripts/iPAGE2
iPAGE_2-0.0.1.dist-info/.DS_Store
iPAGE_2-0.0.1.dist-info/LICENSE
iPAGE_2-0.0.1.dist-info/METADATA
iPAGE_2-0.0.1.dist-info/WHEEL
iPAGE_2-0.0.1.dist-info/top_level.txt
iPAGE_2-0.0.1.dist-info/RECORD
