Metadata-Version: 2.1
Name: iPAGE-2
Version: 0.0.1
Summary: A tool for the pathway analysis of differential gene expression
Home-page: https://github.com/artemy-bakulin/ipage
Author: Artemy Bakulin, Matvei Khoroshkin, Hani Goodarzi
Author-email: artemybakulin@gmail.com
License: UNKNOWN
Platform: UNKNOWN
Classifier: Programming Language :: Python :: 3
Classifier: License :: OSI Approved :: MIT License
Classifier: Operating System :: OS Independent
Requires-Dist: pybiomart
Requires-Dist: statsmodels
Requires-Dist: scipy
Requires-Dist: argparse
Requires-Dist: numpy
Requires-Dist: pandas
Requires-Dist: matplotlib
Requires-Dist: numba (>=0.50.1)
